nomadnet/Conversation.py
nomadnet/Directory.py
nomadnet/Node.py
nomadnet/NomadNetworkApp.py
nomadnet/__init__.py
nomadnet/_version.py
nomadnet/nomadnet.py
nomadnet/util.py
nomadnet/examples/messageboard/README.md
nomadnet/examples/messageboard/messageboard.mu
nomadnet/examples/messageboard/messageboard.py
nomadnet/ui/GraphicalUI.py
nomadnet/ui/MenuUI.py
nomadnet/ui/NoneUI.py
nomadnet/ui/TextUI.py
nomadnet/ui/WebUI.py
nomadnet/ui/__init__.py
nomadnet/ui/textui/Browser.py
nomadnet/ui/textui/Config.py
nomadnet/ui/textui/Conversations.py
nomadnet/ui/textui/Directory.py
nomadnet/ui/textui/Extras.py
nomadnet/ui/textui/Guide.py
nomadnet/ui/textui/Helpers.py
nomadnet/ui/textui/Interfaces.py
nomadnet/ui/textui/Log.py
nomadnet/ui/textui/Main.py
nomadnet/ui/textui/Map.py
nomadnet/ui/textui/MicronParser.py
nomadnet/ui/textui/Network.py
nomadnet/ui/textui/__init__.py
nomadnet/vendor/AsciiChart.py
nomadnet/vendor/Scrollable.py
nomadnet/vendor/__init__.py
nomadnet/vendor/quotes.py
nomadnet/vendor/additional_urwid_widgets/FormWidgets.py
nomadnet/vendor/additional_urwid_widgets/__init__.py
nomadnet/vendor/additional_urwid_widgets/assisting_modules/__init__.py
nomadnet/vendor/additional_urwid_widgets/assisting_modules/modifier_key.py
nomadnet/vendor/additional_urwid_widgets/assisting_modules/useful_functions.py
nomadnet/vendor/additional_urwid_widgets/widgets/__init__.py
nomadnet/vendor/additional_urwid_widgets/widgets/date_picker.py
nomadnet/vendor/additional_urwid_widgets/widgets/indicative_listbox.py
nomadnet/vendor/additional_urwid_widgets/widgets/integer_picker.py
nomadnet/vendor/additional_urwid_widgets/widgets/message_dialog.py
nomadnet/vendor/additional_urwid_widgets/widgets/selectable_row.py
nomadnet-0.9.8.dist-info/licenses/LICENSE
nomadnet-0.9.8.dist-info/METADATA
nomadnet-0.9.8.dist-info/WHEEL
nomadnet-0.9.8.dist-info/entry_points.txt
nomadnet-0.9.8.dist-info/top_level.txt
nomadnet-0.9.8.dist-info/RECORD
