Metadata-Version: 2.4
Name: nomadnet
Version: 0.9.8
Summary: Communicate Freely
Home-page: https://github.com/markqvist/nomadnet
Author: Mark Qvist
Author-email: mark@unsigned.io
Classifier: Programming Language :: Python :: 3
Classifier: License :: OSI Approved :: MIT License
Classifier: Operating System :: OS Independent
Requires-Python: >=3.7
License-File: LICENSE
Requires-Dist: rns>=1.1.3
Requires-Dist: lxmf>=0.9.4
Requires-Dist: urwid>=2.6.16
Requires-Dist: qrcode
Dynamic: author
Dynamic: author-email
Dynamic: classifier
Dynamic: description
Dynamic: description-content-type
Dynamic: home-page
Dynamic: license-file
Dynamic: requires-dist
Dynamic: requires-python
Dynamic: summary
